multi_hurnet/__init__.py
multi_hurnet/multi_hurnet.py
multi_hurnet-1.0.3.dist-info/LICENSE.txt
multi_hurnet-1.0.3.dist-info/METADATA
multi_hurnet-1.0.3.dist-info/WHEEL
multi_hurnet-1.0.3.dist-info/top_level.txt
multi_hurnet-1.0.3.dist-info/RECORD
