Metadata-Version: 2.1
Name: multi-hurnet
Version: 1.0.3
Home-page: https://github.com/
Author: SAPIENS TECHNOLOGY
License: Proprietary Software
License-File: LICENSE.txt
Requires-Dist: numpy
